{
  "components/category/product-listing": "{{inject 'noCompareMessage' (lang 'compare.no_compare')}}\n\n{{#if category.products}}\n    {{> components/products/filter sort=pagination.category.sort}}\n\n    <div {{#if settings.data_tag_enabled}} data-list-name=\"Category: {{category.name}}\" {{/if}}>\n        {{#if theme_settings.product_list_display_mode '===' 'grid'}}\n            {{#if settings.data_tag_enabled}}\n                {{> components/products/grid products=category.products show_compare=category.show_compare theme_settings=theme_settings event=\"list\" }}\n            {{else}}\n                {{> components/products/grid products=category.products show_compare=category.show_compare theme_settings=theme_settings}}\n            {{/if}}\n        {{else}}\n            {{#if settings.data_tag_enabled}}\n                {{> components/products/list products=category.products show_compare=category.show_compare theme_settings=theme_settings event=\"list\" }}\n            {{else}}\n                {{> components/products/list products=category.products show_compare=category.show_compare theme_settings=theme_settings}}\n            {{/if}}\n        {{/if}}\n    </div>\n\n    {{> components/common/paginator pagination.category total=category.total_products}}\n{{else}}\n    {{#if category.search_error}}\n        <p>{{lang 'search.errorMessage'}}</p>\n    {{else}}\n        <p data-no-products-notification\n           role=\"alert\"\n           aria-live=\"assertive\"\n           tabindex=\"-1\"\n        >\n            {{lang 'categories.no_products'}}\n        </p>\n    {{/if}}\n{{/if}}\n",
  "components/products/filter": "<form class=\"actionBar\" method=\"get\" data-sort-by=\"product\">\n    <button class=\"action-toggle-filters\" type=\"button\" data-toggle='{ \"class\": \"--show\", \"target\": \"#faceted-search-container\", \"off\": \"#facetedSearch\" }'>\n        <svg xmlns=\"http://www.w3.org/2000/svg\" width=\"18\" height=\"17\" fill=\"none\" viewBox=\"0 0 18 17\"><path fill=\"#171718\" d=\"M10.4 8c.2-.6.5-1 1-1.4 1.3-.8 3-.2 3.4 1.2 0 .2.2.2.4.2h2.4c.2 0 .4.3.4.5s-.2.4-.4.4h-2.4c-.2 0-.3 0-.4.3-.3 1-1.1 1.5-2.1 1.5s-1.9-.6-2.2-1.5c0-.2-.1-.3-.3-.3H.5C.2 9 0 8.8 0 8.5c0-.3.2-.5.5-.5h9.9Zm3.6.5c0-.8-.6-1.3-1.3-1.4-.8 0-1.4.6-1.4 1.4 0 .7.6 1.3 1.4 1.3.7 0 1.3-.6 1.3-1.3ZM1.9 1.8C2.2.7 2.9 0 4 0s2 .6 2.3 1.8h11.3c.2 0 .4.2.4.5 0 .2-.2.3-.4.4h-11c-.2 0-.3 0-.4.2C6 4 5.1 4.5 4.1 4.5s-1.9-.6-2.2-1.6c0-.2-.1-.2-.3-.2h-1c-.4 0-.6-.2-.6-.4 0-.3.2-.5.5-.5h1.3Zm.8.4c0 .8.6 1.4 1.4 1.4.7 0 1.3-.6 1.3-1.3 0-.8-.6-1.4-1.3-1.4-.8 0-1.4.6-1.4 1.3Zm-.8 12.1A2.3 2.3 0 0 1 4 12.5c1 0 2 .6 2.2 1.8h11.2c.3 0 .5.2.5.4 0 .3-.2.5-.5.5H6.6c-.2 0-.3 0-.3.2C6 16.4 5 17 4 17c-1 0-1.8-.6-2.2-1.5 0-.3-.1-.3-.4-.3h-1c-.3 0-.5-.2-.5-.5s.2-.4.6-.4h1.3Zm.8.4c0 .8.6 1.4 1.4 1.4.7 0 1.3-.6 1.3-1.3 0-.8-.6-1.4-1.3-1.4-.8 0-1.4.6-1.4 1.3Z\"/></svg>\n        <span>{{lang \"category.filters\"}}</span>\n        <svg width=\"11\" height=\"16\" viewBox=\"0 0 11 16\" fill=\"none\" xmlns=\"http://www.w3.org/2000/svg\"><path d=\"M3 3L8 8L3 13\" stroke=\"#171718\" stroke-width=\"3\" stroke-linecap=\"square\"/></svg>\n    </button>\n\n    {{> components/category/sort-box sort=sort}}\n</form>\n",
  "components/products/grid": "<ul class=\"productGrid\">\n    {{#each products}}\n    <li class=\"product\">\n            {{>components/products/card settings=../settings show_compare=../show_compare show_rating=../settings.show_product_rating theme_settings=../theme_settings customer=../customer event=../event position=(add @index 1)}}\n    </li>\n    {{/each}}\n</ul>\n",
  "components/products/list": "<ul class=\"productList\">\n    {{#each products}}\n    <li class=\"product\">\n\t\t{{>components/products/list-item show_compare=../show_compare show_rating=../settings.show_product_rating theme_settings=../theme_settings customer=../customer event=../event settings=../settings position=(add @index 1)}}\n    </li>\n    {{/each}}\n</ul>\n",
  "components/common/paginator": "<nav class=\"pagination\" aria-label=\"pagination\"></nav>\n    {{#if total}}\n    <p class=\"pagination-summary\">\n        {{{lang \"category.viewed\" upto=end total=total}}}\n    </p>\n    {{/if}}\n\n    <ul class=\"pagination-list\">\n        {{#if previous}}\n            <li class=\"pagination-item pagination-item--previous\">\n                <a class=\"pagination-link\"\n                   href=\"{{previous}}\"\n                   {{#unless reload}}data-faceted-search-facet{{/unless}}\n                   aria-label=\"{{lang 'common.previous'}}\"\n                >                    \n                    <svg width=\"13\" height=\"19\" viewBox=\"0 0 13 19\" fill=\"none\" xmlns=\"http://www.w3.org/2000/svg\">\n                        <path d=\"M9.45605 15.1973L3.10671 9.37703L9.45606 3.5568\" stroke=\"white\" stroke-width=\"4\" stroke-linecap=\"square\"/>\n                    </svg>    \n                </a>\n            </li>\n        {{/if}}\n        {{#each links}}\n            <li class=\"pagination-item {{#if this.number '==' ../current}}pagination-item--current{{/if}}\">\n                <a class=\"pagination-link\"\n                   href=\"{{this.url}}\"\n                   {{#unless reload}}data-faceted-search-facet{{/unless}}\n                   {{#if this.number '==' ../current}}\n                   aria-current=\"page\"\n                   data-pagination-current-page-link\n                   {{/if}}\n                   aria-label=\"{{lang 'common.paginator.page_of' current=this.number total=../links.length}}\"\n                >\n                    {{this.number}}\n                </a>\n            </li>\n        {{/each}}\n\n        {{#if next}}\n            <li class=\"pagination-item pagination-item--next\">\n                <a class=\"pagination-link\"\n                   href=\"{{next}}\"\n                   {{#unless reload}}data-faceted-search-facet{{/unless}}\n                   aria-label=\"{{lang 'common.next'}}\"\n                >\n                    <svg width=\"13\" height=\"19\" viewBox=\"0 0 13 19\" fill=\"none\" xmlns=\"http://www.w3.org/2000/svg\">\n                        <path d=\"M3.42822 3.55676L9.77757 9.377L3.42822 15.1972\" stroke=\"white\" stroke-width=\"4\" stroke-linecap=\"square\"/>\n                    </svg>\n                </a>\n            </li>\n        {{/if}}\n    </ul>\n</nav>\n",
  "components/category/sort-box": "<fieldset class=\"form-fieldset actionBar-section\">\n    <div class=\"form-field form-field--per-page\">\n        <label class=\"form-label\" for=\"limit\">{{lang 'category.show'}}</label>\n\n        <select class=\"form-select form-select-small\" name=\"limit\" id=\"limit\" onchange=\"location='?limit='+this.value\">\n            <option value=\"6\" {{#if '6' '==' theme_settings.categorypage_products_per_page }}selected{{/if}}>6</option>\n            <option value=\"8\" {{#if '8' '==' theme_settings.categorypage_products_per_page }}selected{{/if}}>8</option>\n            <option value=\"9\" {{#if '9' '==' theme_settings.categorypage_products_per_page }}selected{{/if}}>9</option>\n            <option value=\"12\" {{#if '12' '==' theme_settings.categorypage_products_per_page }}selected{{/if}}>12</option>\n            <option value=\"15\" {{#if '15' '==' theme_settings.categorypage_products_per_page }}selected{{/if}}>15</option>\n            <option value=\"16\" {{#if '16' '==' theme_settings.categorypage_products_per_page }}selected{{/if}}>16</option>\n            <option value=\"18\" {{#if '18' '==' theme_settings.categorypage_products_per_page }}selected{{/if}}>18</option>\n            <option value=\"20\" {{#if '20' '==' theme_settings.categorypage_products_per_page }}selected{{/if}}>20</option>\n            <option value=\"24\" {{#if '24' '==' theme_settings.categorypage_products_per_page }}selected{{/if}}>24</option>\n            <option value=\"30\" {{#if '36' '==' theme_settings.categorypage_products_per_page }}selected{{/if}}>30</option>\n        </select>\n\n        <label class=\"form-label\" for=\"limit\"> {{lang 'category.per_page'}}</label>\n        <script>\n            (function() {\n                try {\n                    var url = new URL(window.location.href);\n                    var c = url.searchParams.get(\"limit\");\n                    if (c != null) {\n                        var limit = document.querySelectorAll('select#limit option');\n                        Array.prototype.forEach.call(limit, function(element) {\n                            if (element.value == c) {\n                                element.selected = true;\n                            }\n                        });\n                    }\n                } catch (e) {}\n            }());\n        </script>\n    </div>\n\n    <div class=\"form-field form-field--sort-by\">\n        <label class=\"form-label\" for=\"sort\">\n            <span>{{lang 'category.sort_by'}}</span>\n            <svg width=\"15\" height=\"10\" viewBox=\"0 0 15 10\" fill=\"none\" xmlns=\"http://www.w3.org/2000/svg\"><path d=\"M12.5 2.5L7.5 7.5L2.5 2.5\" stroke=\"#171718\" stroke-width=\"3\" stroke-linecap=\"square\"/></svg>\n        </label>\n\n        <select class=\"form-select form-select--small \" name=\"sort\" id=\"sort\" role=\"listbox\">\n            <option value=\"featured\" {{#if sort '==' 'featured'}}selected{{/if}}>{{lang 'common.sorter.featured'}}</option>\n            <option value=\"newest\" {{#if sort '==' 'newest'}}selected{{/if}}>{{lang 'common.sorter.newest'}}</option>\n            <option value=\"bestselling\" {{#if sort '==' 'bestselling'}}selected{{/if}}>{{lang 'common.sorter.top_sellers'}}</option>\n            <option value=\"alphaasc\" {{#if sort '==' 'alphaasc'}}selected{{/if}}>{{lang 'common.sorter.alpha_asc'}}</option>\n            <option value=\"alphadesc\" {{#if sort '==' 'alphadesc'}}selected{{/if}}>{{lang 'common.sorter.alpha_desc'}}</option>\n            <option value=\"avgcustomerreview\" {{#if sort '==' 'avgcustomerreview'}}selected{{/if}}>{{lang 'common.sorter.reviews'}}</option>\n            <option value=\"priceasc\" {{#if sort '==' 'priceasc'}}selected{{/if}}>{{lang 'common.sorter.price_asc'}}</option>\n            <option value=\"pricedesc\" {{#if sort '==' 'pricedesc'}}selected{{/if}}>{{lang 'common.sorter.price_desc'}}</option>\n            {{#if result_count}}\n                <option value=\"relevance\" {{#if sort '==' 'relevance'}}selected{{/if}}>{{lang 'common.sorter.relevance'}}</option>\n            {{/if}}\n        </select>\n    </div>\n</fieldset>\n",
  "components/products/card": "<article\n    class=\"card card-product\n    {{#if alternate}} card--alternate{{/if}}\"\n    data-product=\"card-{{id}}\"\n    data-product-id=\"{{id}}\"\n    data-product-category=\"{{#each category}}{{#if @last}}{{this}}{{else}}{{this}},{{/if}}{{/each}}\"\n    {{#if settings.data_tag_enabled}}\n        data-event-type=\"{{event}}\"\n        data-entity-id=\"{{id}}\"\n        data-position=\"{{position}}\"\n        data-name=\"{{name}}\"\n        data-product-brand=\"{{brand.name}}\"\n        data-product-price=\"\n        {{#or customer (unless theme_settings.restrict_to_login)}}\n            {{#if price.with_tax}}\n                {{price.with_tax.value}}\n            {{else}}\n                {{price.without_tax.value}}\n            {{/if}}\n        {{else}}\n            {{lang 'common.login_for_pricing'}}\n        {{/or}}\"\n    {{/if}}>\n    <figure class=\"card-figure\">\n        {{#if stock_level '===' 0}}\n            {{#if theme_settings.pdp_sold_out_label '===' ''}}\n                {{> components/products/product-badge\n                    badge-type='sold-out'\n                    badge_view=theme_settings.product_sold_out_badges\n                    badge_label=(lang \"page_builder.pdp_sold_out_label\")\n                }}\n            {{else}}\n                {{> components/products/product-badge\n                    badge-type='sold-out'\n                    badge_view=theme_settings.product_sold_out_badges\n                    badge_label=theme_settings.pdp_sold_out_label\n                }}\n            {{/if}}\n        {{else}}\n            {{#or price.sale_price_with_tax.value price.sale_price_without_tax.value}}\n                {{#if theme_settings.pdp_sale_badge_label '===' ''}}\n                    {{> components/products/product-badge\n                        badge-type='sale'\n                        badge_view=theme_settings.product_sale_badges\n                        badge_label=(lang \"page_builder.pdp_sale_badge_label\")\n                    }}\n                {{else}}\n                    {{> components/products/product-badge\n                        badge-type='sale'\n                        badge_view=theme_settings.product_sale_badges\n                        badge_label=theme_settings.pdp_sale_badge_label\n                    }}\n                {{/if}}\n            {{/or}}\n        {{/if}}\n\n        <a href=\"{{url}}\"\n           class=\"card-figure__link\"\n           aria-label=\"{{> components/products/product-info}}\"\n           {{#if settings.data_tag_enabled}} data-event-type=\"product-click\" {{/if}}\n        >\n            <div class=\"card-img-container\">\n                {{> components/common/responsive-img\n                    image=image\n                    class=\"card-image\"\n                    fallback_size=theme_settings.productgallery_size\n                    lazyload=theme_settings.lazyload_mode\n                    default_image=theme_settings.default_image_product\n                }}\n            </div>\n        </a>\n\n        <figcaption class=\"card-figcaption\">\n            <div class=\"card-figcaption-body\">\n                {{!-- {{#unless hide_product_quick_view}}\n                    {{#if theme_settings.show_product_quick_view}}\n                        {{#if settings.data_tag_enabled}}\n                            <button type=\"button\" class=\"button button--small card-figcaption-button quickview\" data-event-type=\"product-click\" data-product-id=\"{{id}}\">{{lang 'products.quick_view'}}</button>\n                        {{else}}\n                            <button type=\"button\" class=\"button button--small card-figcaption-button quickview\" data-product-id=\"{{id}}\">{{lang 'products.quick_view'}}</button>\n                        {{/if}}\n                    {{/if}}\n                {{/unless}} --}}\n                {{#if show_compare}}\n                    <label class=\"button button--small card-figcaption-button\" for=\"compare-{{id}}\">\n                        {{lang 'products.compare'}} <input type=\"checkbox\" name=\"products[]\" value=\"{{id}}\" id=\"compare-{{id}}\" data-compare-id=\"{{id}}\">\n                    </label>\n                {{/if}}\n                {{#or customer (if theme_settings.restrict_to_login '!==' true)}}\n                    {{#if show_cart_action}}\n                        {{!-- {{#if has_options}}\n                            <a href=\"{{url}}\" data-event-type=\"product-click\" class=\"button button--small card-figcaption-button\" data-product-id=\"{{id}}\">{{lang 'products.choose_options'}}</a>\n                        {{/if}} --}}\n                        {{#if pre_order}}\n                            <a href=\"{{pre_order_add_to_cart_url}}\" data-event-type=\"product-click\" class=\"button button--small card-figcaption-button\">{{lang 'products.pre_order'}}</a>\n                        {{/if}}\n                        {{#if add_to_cart_url }}\n                            <a href=\"{{add_to_cart_url}}\" data-event-type=\"product-click\" data-button-type=\"add-cart\" class=\"button button--small card-figcaption-button\">{{lang 'products.add_to_cart'}}</a>\n                            <span class=\"product-status-message aria-description--hidden\">{{lang 'category.add_cart_announcement'}}</span>\n                        {{/if}}\n                        {{#if out_of_stock_message }}\n                            <a href=\"{{url}}\" data-event-type=\"product-click\" class=\"button button--small card-figcaption-button\" data-product-id=\"{{id}}\">{{out_of_stock_message}}</a>\n                        {{/if}}\n                    {{/if}}\n                {{/or}}\n            </div>\n        </figcaption>\n    </figure>\n    <div class=\"card-body {{#if customer '===' null}}guest{{/if}}\">\n        {{#and rating show_rating}}\n            <p class=\"card-text\" data-test-info-type=\"productRating\">\n                <span class=\"rating--small\">\n                    {{> components/products/ratings rating_target=name rating=rating}}\n                </span>\n            </p>\n        {{/and}}\n        {{#if brand.name}}\n            <p class=\"card-text\" data-test-info-type=\"brandName\">{{brand.name}}</p>\n        {{/if}}\n        <h3 class=\"card-title\">\n            <a aria-label=\"{{> components/products/product-info}}\"\n               href=\"{{url}}\"\n               {{#if settings.data_tag_enabled}} data-event-type=\"product-click\" {{/if}}\n            >\n                {{name}}\n            </a>\n        </h3>\n        <div class=\"card-info\">\n            <div class=\"card-sku\">\n                <span>{{lang \"products.sku\"}}</span> {{sku}}\n            </div>\n\n            {{#if out_of_stock_message }}\n            <div class=\"card-stock --out-of-stock\">\n                {{lang \"products.out_of_stock\"}}\n            </div>\n            {{else}}\n            <div class=\"card-stock --in-stock\">\n                {{lang \"products.in_stock\"}}\n            </div>\n            {{/if}}\n        </div>\n\n        <div class=\"card-text card-text--price\" data-test-info-type=\"price\">\n            {{#unless customer}}\n                {{> components/common/login-for-pricing}}\n            {{/unless}}\n\n            {{#if this.price}}\n                {{> components/products/price price=price}}\n            {{/if}}\n        </div>\n\n        {{> components/products/bulk-discount-rates}}\n\n        {{#if has_options}}\n        <a href=\"{{url}}\" class=\"button button-add-to-cart\" data-product-id=\"{{id}}\" data-event-type=\"product-click\">\n            <svg width=\"22\" height=\"21\" viewBox=\"0 0 22 21\" fill=\"none\" xmlns=\"http://www.w3.org/2000/svg\">\n                <path d=\"M1 1H4.63636L7.07273 13.1148C7.15586 13.5313 7.38355 13.9055 7.71595 14.1718C8.04835 14.4381 8.46427 14.5796 8.89091 14.5714H17.7273C18.1539 14.5796 18.5698 14.4381 18.9022 14.1718C19.2346 13.9055 19.4623 13.5313 19.5455 13.1148L21 5.52381H5.54545M9.18182 19.0952C9.18182 19.5949 8.7748 20 8.27273 20C7.77065 20 7.36364 19.5949 7.36364 19.0952C7.36364 18.5956 7.77065 18.1905 8.27273 18.1905C8.7748 18.1905 9.18182 18.5956 9.18182 19.0952ZM19.1818 19.0952C19.1818 19.5949 18.7748 20 18.2727 20C17.7707 20 17.3636 19.5949 17.3636 19.0952C17.3636 18.5956 17.7707 18.1905 18.2727 18.1905C18.7748 18.1905 19.1818 18.5956 19.1818 19.0952Z\" stroke=\"white\" stroke-width=\"1.5\" stroke-linecap=\"round\" stroke-linejoin=\"round\"/>\n            </svg>\n            <span>{{lang \"products.choose_option\"}}</span>\n        </a>\n        {{else}}\n            {{#if add_to_cart_url}}\n                <button type=\"button\" class=\"button button-add-to-cart quickview\" data-product-id=\"{{id}}\">\n                    <svg width=\"22\" height=\"21\" viewBox=\"0 0 22 21\" fill=\"none\" xmlns=\"http://www.w3.org/2000/svg\">\n                        <path d=\"M1 1H4.63636L7.07273 13.1148C7.15586 13.5313 7.38355 13.9055 7.71595 14.1718C8.04835 14.4381 8.46427 14.5796 8.89091 14.5714H17.7273C18.1539 14.5796 18.5698 14.4381 18.9022 14.1718C19.2346 13.9055 19.4623 13.5313 19.5455 13.1148L21 5.52381H5.54545M9.18182 19.0952C9.18182 19.5949 8.7748 20 8.27273 20C7.77065 20 7.36364 19.5949 7.36364 19.0952C7.36364 18.5956 7.77065 18.1905 8.27273 18.1905C8.7748 18.1905 9.18182 18.5956 9.18182 19.0952ZM19.1818 19.0952C19.1818 19.5949 18.7748 20 18.2727 20C17.7707 20 17.3636 19.5949 17.3636 19.0952C17.3636 18.5956 17.7707 18.1905 18.2727 18.1905C18.7748 18.1905 19.1818 18.5956 19.1818 19.0952Z\" stroke=\"white\" stroke-width=\"1.5\" stroke-linecap=\"round\" stroke-linejoin=\"round\"/>\n                    </svg>\n                    <span>{{lang 'products.add_to_cart'}}</span>\n                </button>\n            {{else}}\n                <a href=\"{{#if add_to_cart_url }}{{add_to_cart_url}}{{else}}{{url}}{{/if}}\" class=\"button button-add-to-cart\" data-product-id=\"{{id}}\" data-event-type=\"product-click\" {{#if add_to_cart_url }}data-action=\"addtocart\"{{/if}}>\n                    <svg width=\"22\" height=\"21\" viewBox=\"0 0 22 21\" fill=\"none\" xmlns=\"http://www.w3.org/2000/svg\">\n                        <path d=\"M1 1H4.63636L7.07273 13.1148C7.15586 13.5313 7.38355 13.9055 7.71595 14.1718C8.04835 14.4381 8.46427 14.5796 8.89091 14.5714H17.7273C18.1539 14.5796 18.5698 14.4381 18.9022 14.1718C19.2346 13.9055 19.4623 13.5313 19.5455 13.1148L21 5.52381H5.54545M9.18182 19.0952C9.18182 19.5949 8.7748 20 8.27273 20C7.77065 20 7.36364 19.5949 7.36364 19.0952C7.36364 18.5956 7.77065 18.1905 8.27273 18.1905C8.7748 18.1905 9.18182 18.5956 9.18182 19.0952ZM19.1818 19.0952C19.1818 19.5949 18.7748 20 18.2727 20C17.7707 20 17.3636 19.5949 17.3636 19.0952C17.3636 18.5956 17.7707 18.1905 18.2727 18.1905C18.7748 18.1905 19.1818 18.5956 19.1818 19.0952Z\" stroke=\"white\" stroke-width=\"1.5\" stroke-linecap=\"round\" stroke-linejoin=\"round\"/>\n                    </svg>\n                    <span>{{lang \"products.add_to_cart\"}}</span>\n                </a>\n            {{/if}}\n        {{/if}}\n\n        <div class=\"card-wishlist\" data-wishlist-add>\n            <button class=\"js-wishlist\" data-id=\"{{id}}\">\n                <svg width=\"23\" height=\"20\" viewBox=\"0 0 23 20\" fill=\"none\" xmlns=\"http://www.w3.org/2000/svg\">\n                    <path d=\"M20.2913 2.61183C19.7805 2.10083 19.1741 1.69547 18.5066 1.41891C17.8392 1.14235 17.1238 1 16.4013 1C15.6788 1 14.9634 1.14235 14.2959 1.41891C13.6285 1.69547 13.022 2.10083 12.5113 2.61183L11.4513 3.67183L10.3913 2.61183C9.3596 1.58013 7.96032 1.00053 6.50129 1.00053C5.04226 1.00053 3.64298 1.58013 2.61129 2.61183C1.5796 3.64352 1 5.04279 1 6.50183C1 7.96086 1.5796 9.36013 2.61129 10.3918L11.4513 19.2318L20.2913 10.3918C20.8023 9.88107 21.2076 9.27464 21.4842 8.60718C21.7608 7.93972 21.9031 7.22431 21.9031 6.50183C21.9031 5.77934 21.7608 5.06393 21.4842 4.39647C21.2076 3.72901 20.8023 3.12258 20.2913 2.61183Z\" stroke=\"#171718\" stroke-width=\"1.5\" stroke-linecap=\"round\" stroke-linejoin=\"round\"/>\n                </svg>\n            </button>\n\n            <ul class=\"wishlist-menu\">\n                <li>\n                    <a href=\"/wishlist.php?action=addwishlist&product_id={{id}}\">{{lang \"account.wishlists.create_new\"}}</a>\n                </li>\n            </ul>\n        </div>\n    </div>\n</article>\n",
  "components/products/list-item": "{{#if settings.data_tag_enabled}}\n    <article class=\"listItem\" data-event-type=\"{{event}}\" data-entity-id=\"{{id}}\" data-position=\"{{position}}\" data-name=\"{{name}}\" data-product-category=\"{{#each category}}{{#if @last}}{{this}}{{else}}{{this}}, {{/if}}{{/each}}\" data-product-brand=\"{{brand.name}}\" data-product-price=\"\n    {{#or customer (unless theme_settings.restrict_to_login)}}\n        {{#if price.with_tax}}\n            {{price.with_tax.value}}\n        {{else}}\n            {{price.without_tax.value}}\n        {{/if}}\n    {{else}}\n        {{lang 'common.login_for_pricing'}}\n    {{/or}}\">\n{{else}}\n    <article class=\"listItem\">\n{{/if}}\n    <figure class=\"listItem-figure\">\n        <a href=\"{{url}}\"\n           class=\"listItem-figure__link\"\n           aria-label=\"{{> components/products/product-info}}\"\n           {{#if settings.data_tag_enabled}}\n           data-event-type=\"product-click\"\n           {{/if}}\n        >\n        {{#if stock_level '===' 0}}\n            {{#if theme_settings.pdp_sold_out_label '===' ''}}\n                {{> components/products/product-badge\n                    badge-type='sold-out'\n                    badge_view=theme_settings.product_sold_out_badges\n                    badge_label=(lang \"page_builder.pdp_sold_out_label\")\n                }}\n            {{else}}\n                {{> components/products/product-badge\n                    badge-type='sold-out'\n                    badge_view=theme_settings.product_sold_out_badges\n                    badge_label=theme_settings.pdp_sold_out_label\n                }}\n            {{/if}}\n        {{else}}\n            {{#or price.sale_price_with_tax.value price.sale_price_without_tax.value}}\n                {{#if theme_settings.pdp_sale_badge_label '===' ''}}\n                    {{> components/products/product-badge\n                        badge-type='sale'\n                        badge_view=theme_settings.product_sale_badges\n                        badge_label=(lang \"page_builder.pdp_sale_badge_label\")\n                    }}\n                {{else}}\n                    {{> components/products/product-badge\n                        badge-type='sale'\n                        badge_view=theme_settings.product_sale_badges\n                        badge_label=theme_settings.pdp_sale_badge_label\n                    }}\n                {{/if}}\n            {{/or}}\n        {{/if}}\n        {{> components/common/responsive-img\n            image=image\n            class=\"listItem-image\"\n            fallback_size=theme_settings.productgallery_size\n            lazyload=theme_settings.lazyload_mode\n            default_image=theme_settings.default_image_product\n        }}\n        </a>\n        {{#unless hide_product_quick_view}}\n            {{#if theme_settings.show_product_quick_view}}\n                <div class=\"listItem-figureBody\">\n                    <button type=\"button\" {{#if settings.data_tag_enabled}} data-event-type=\"product-click\" {{/if}} class=\"button button--small listItem-button quickview\" data-product-id=\"{{id}}\">{{lang 'products.quick_view'}}</button>\n                </div>\n            {{/if}}\n        {{/unless}}\n    </figure>\n    <div class=\"listItem-body\">\n        <div class=\"listItem-content\">\n            <div class=\"listItem-details\">\n                {{#if show_rating}}\n                    <p class=\"listItem-rating\">{{> components/products/ratings rating_target=name rating=rating}}</p>\n                {{/if}}\n                {{#if brand.name}}\n                <p class=\"listItem-brand\">{{brand.name}}</p>\n                {{/if}}\n                <h4 class=\"listItem-title\">\n                    <a href=\"{{url}}\"\n                    aria-label=\"{{> components/products/product-info}}\"\n                    {{#if settings.data_tag_enabled}}\n                    data-event-type=\"product-click\"\n                    {{/if}}\n                    >\n                        {{name}}\n                    </a>\n                </h4>\n                {{#if summary}}\n                    <p>{{{summary}}}</p>\n                {{/if}}\n            </div>\n            <div class=\"listItem-actions\">\n                {{#or customer (if theme_settings.restrict_to_login '!==' true)}}\n                    {{#if price}}\n                        <div class=\"listItem-price\">{{> components/products/price price=price}}</div>\n                    {{/if}}\n                    {{#if show_cart_action}}\n                        {{#if has_options}}\n                            <a href=\"{{url}}\" {{#if settings.data_tag_enabled}} data-event-type=\"product-click\" {{/if}} class=\"button button--small\" data-product-id=\"{{id}}\">{{lang 'products.choose_options'}}</a>\n                        {{/if}}\n                        {{#if pre_order}}\n                            <a href=\"{{pre_order_add_to_cart_url}}\" data-event-type=\"product-click\" class=\"button button--primary\">{{lang 'products.pre_order'}}</a>\n                        {{/if}}\n                        {{#if add_to_cart_url }}\n                            <a href=\"{{add_to_cart_url}}\" {{#if settings.data_tag_enabled}} data-event-type=\"product-click\" {{/if}} class=\"button button--primary\">{{lang 'products.add_to_cart'}}</a>\n                        {{/if}}\n                        {{#if out_of_stock_message }}\n                            <a href=\"{{url}}\" data-event-type=\"product-click\" class=\"button button--small\" data-product-id=\"{{id}}\">{{out_of_stock_message}}</a>\n                        {{/if}}\n                    {{/if}}\n                {{else}}\n                    {{> components/common/login-for-pricing}}\n                {{/or}}\n                {{#if show_compare}}\n                    <label class=\"button button--small\" for=\"compare-{{id}}\">\n                        {{lang \"products.compare\"}} <input type=\"checkbox\" name=\"products[]\" value=\"{{id}}\" id=\"compare-{{id}}\" data-compare-id=\"{{id}}\">\n                    </label>\n                {{/if}}\n            </div>\n        </div>\n    </div>\n</article>\n",
  "components/products/product-badge": "{{#if badge_view '===' 'sash'}}\n    <div class=\"{{badge-type}}-flag-sash\">\n        <span class=\"{{badge-type}}-text\">{{{badge_label}}}</span>\n    </div>\n{{else if badge_view '===' 'topleft'}}\n    <div class=\"{{badge-type}}-flag-side\">\n        <span class=\"{{badge-type}}-text\">{{{badge_label}}}</span>\n    </div>\n{{else if badge_view '===' 'burst'}}\n    <div class=\"starwrap\">\n        <div class=\"{{badge-type}}-text-burst\">{{{badge_label}}}</div>\n        <div class=\"{{badge-type}}-flag-star\"></div>\n    </div>\n{{/if}}\n",
  "components/products/ratings": "<span role=\"img\"\n    {{#if rating_target}}\n      aria-label=\"{{lang 'products.reviews.rating_aria_label' rating_target=rating_target current_rating=rating max_rating=5}}\"\n    {{else}}\n      aria-label=\"{{lang 'products.reviews.rating_aria_label' rating_target='Product' current_rating=rating max_rating=5}}\"\n    {{/if}}\n>\n    {{#for 1 5}}\n        {{#if ../this.rating '>=' $index}}\n            <span class=\"icon icon--ratingFull\">\n                <svg>\n                    <use xlink:href=\"#icon-star\" />\n                </svg>\n            </span>\n        {{else}}\n            <span class=\"icon icon--ratingEmpty\">\n                <svg>\n                    <use xlink:href=\"#icon-star\" />\n                </svg>\n            </span>\n        {{/if}}\n    {{/for}}\n</span>\n",
  "components/common/responsive-img": "{{!--\nThis file implements the lazysizes srcset pattern (as seen on\nhttps://github.com/aFarkas/lazysizes#modern-transparent-srcset-pattern) for maximum performance on modern browsers\nand reasonable compatibility with legacy browsers.\n\nThere are a few important arguments to know about when using this component:\n`lazyload`:\n    - If set to 'lazyload+lqip', will load a low-res image which will be replaced by lazysizes - ensuring that SOME\n    content is shown immediately on page load. Without LQIP, a transparent gif will be used instead, which reduces\n    the number of requests needed to load the page, making it even faster.\n    - If set to 'lazyload', the browser will not load the full-size image at first, instead the lazysizes plugin will\n        load it progressively after page load. This improves the load speed of the page, but it should be disabled for\n        high-priority above-the-fold images.\n    - If set to 'disabled', will not attempt to lazyload the image and instead tell the browser to load it immediately.\n        Use this for high-priority images that are above the fold.\n\n`fallback_size`:\n    This is the size to use for this image in legacy browsers that do not support srcset.\n    Can be defined as a pixel bounding-box size (e.g. \"123x123) or inherent width (e.g. \"123w\").\n\n`class`:\n    The CSS classes to add to the image, e.g. \"card-image\". If lazyloading is enabled, all images will have the\n    \"lazyload\" class so that lazysizes will target them automatically.\n\n`otherAttributes`:\n    Any other HTML attributes you want on the img tag, for example \"height='100' width='100'\"\n\n`default_image`:\n    The default image to use if `image` is undefined or falsy. Should be a theme asset, usually defined as a relative\n    path in the theme config. If a default image is not provided, you'll get an image tag with no image if the primary\n    image is undefined.\n\n`lqip_size`:\n    If you want to specify a particular size for the LQIP image, you can do so with this argument. A default of 80\n    pixels wide will be used otherwise. This argument has no effect if the lazyload mode is not \"lazyload+lqip\".\n\n--}}\n<img {{#if image}}{{!-- Get the default image for legacy browsers that do not support srcset\n--}}src=\"{{getImageSrcset image 1x=(default fallback_size '160w')}}\" alt=\"{{image.alt}}\" title=\"{{image.alt}}\" {{!--\n  Allow lazysizes to generate the 'sizes' attribute automatically --}}data-sizes=\"auto\"\n  {{#unless lazyload '==' 'disabled'}}\n    {{#if lazyload '==' 'lazyload+lqip'}}\n    {{!-- If we want a LQIP, include it as the default srcset (will be overwritten by lazysizes) --}}\n    srcset=\"{{getImageSrcset image 1x=(default lqip_size '80w')}}\"\n    {{else}}\n      {{!-- If we don't want a LQIP, use a 1px transparent gif for the stand-in image\n            This requires no additional network request, so it's fast --}}\n    srcset=\"data:image/gif;base64,R0lGODlhAQABAIAAAP///wAAACH5BAEAAAAALAAAAAABAAEAAAICRAEAOw==\"\n    {{/if}}\n{{/unless}}\n{{!-- If lazyloading is disabled, just use \"srcset\". If it is not disabled, use \"data-srcset\" so lazysizes will use\n      this after page load --}}\n{{!--\nGenerate the srcset string using the default sizes defined in the helper. This will allow the browser to\npick the best-sized image based on its own understanding of how it will render the page.\n--}}\n{{#unless lazyload '==' 'disabled'}}data-{{/unless}}srcset=\"{{getImageSrcset image use_default_sizes=true }}\"\n{{else if default_image}}src=\"{{cdn default_image}}\" alt=\"{{lang 'products.card_default_image_alt'}}\"{{/if}}\nclass=\"{{#unless lazyload '==' 'disabled'}}lazyload{{/unless}}{{#if class}} {{class}}{{/if}}\"\n{{#if lazyload '==' 'lazyload'}}loading=\"lazy\"{{/if}}\n{{otherAttributes}} />\n",
  "components/products/product-info": "{{#or customer (unless theme_settings.restrict_to_login)}}\n{{name}}, {{> components/products/product-aria-label}}\n{{else}}\n{{name}}\n{{/or}}\"\n",
  "components/common/login-for-pricing": "<p class=\"price-login\" translate><a href=\"/login.php\">{{lang 'common.login_for_pricing'}}</a></p>\n",
  "components/products/bulk-discount-rates": "{{#if bulk_discount_rates.length}}\n    {{#if product}}<dt class=\"productView-info-name\">{{lang 'products.bulk_pricing.title'}}</dt>{{/if}}\n    <dd class=\"productView-info-value\">\n        <a href=\"{{product.url}}#bulk_pricing\"\n           {{#unless is_ajax }}data-reveal-id=\"modal-bulk-pricing\"{{/unless}}>\n            {{lang 'products.bulk_pricing.view'}}\n        </a>\n    </dd>\n    <div id=\"modal-bulk-pricing\" class=\"modal modal--small\" data-reveal>\n        <div class=\"modal-header\">\n            <h2 class=\"modal-header-title\">{{lang 'products.bulk_pricing.modal_title'}}</h2>\n            {{> components/common/modal/modal-close-btn}}\n        </div>\n        <div class=\"modal-body\">\n            <p>{{lang 'products.bulk_pricing.instructions'}}</p>\n            <ul>\n                {{#each bulk_discount_rates}}\n                <li>\n                    {{lang 'products.bulk_pricing.range' min=min max=max}}\n                    {{#if type '===' 'percent'}}\n                    {{lang 'products.bulk_pricing.percent' discount=discount.formatted}}\n                    {{else if type '===' 'fixed'}}\n                    {{lang 'products.bulk_pricing.fixed' discount=discount.formatted}}\n                    {{else if type '===' 'price'}}\n                    {{lang 'products.bulk_pricing.price' discount=discount.formatted}}\n                    {{/if}}\n                </li>\n                {{/each}}\n            </ul>\n        </div>\n    </div>\n{{/if}}\n",
  "components/products/price": "{{!-- There are 2 code paths for generating the PDP pricing HTML determined by the following #and condition.\nIf a 'price_range' exists then we generate all HTML in price-range.html, otherwise it is defined here. Both code\npaths generate the same HTML structure with some differences in whether that element is displayed by default (css styling).\n\nIf you are making a change here or in price-range.html, you probably want to make that change in both files. --}}\n\n{{#and price.price_range (if theme_settings.price_ranges '==' true)}}\n    {{> components/products/price-range price=price}}\n{{else}}\n    {{#if price.with_tax}}\n        <div class=\"price-section price-section--withTax rrp-price--withTax\" {{#unless price.rrp_with_tax}}style=\"display: none;\"{{/unless}}>\n            <span>\n                {{> components/products/price-label\n                    label_value=theme_settings.pdp-retail-price-label\n                    fallback=(lang \"page_builder.pdp-retail-price-label\")\n                }}\n            </span>\n            <span data-product-rrp-with-tax class=\"price price--rrp\">\n                {{price.rrp_with_tax.formatted}}\n            </span>\n        </div>\n        <div class=\"price-section price-section--withTax non-sale-price--withTax\" {{#unless price.non_sale_price_with_tax}}style=\"display: none;\"{{/unless}}>\n            <span>\n                {{> components/products/price-label\n                    label_value=theme_settings.pdp-non-sale-price-label\n                    fallback=(lang \"page_builder.pdp-non-sale-price-label\")\n                }}\n            </span>\n            <span data-product-non-sale-price-with-tax class=\"price price--non-sale\">\n                {{price.non_sale_price_with_tax.formatted}}\n            </span>\n        </div>\n        <div class=\"price-section price-section--withTax\">\n            <span class=\"price-label\" {{#if price.non_sale_price_with_tax}}style=\"display: none;\"{{/if}}>\n                {{theme_settings.pdp-price-label}}\n            </span>\n            <span class=\"price-now-label\" {{#unless price.non_sale_price_with_tax}}style=\"display: none;\"{{/unless}}>\n                {{> components/products/price-label\n                    label_value=theme_settings.pdp-sale-price-label\n                    fallback=(lang \"page_builder.pdp-sale-price-label\")\n                }}\n            </span>\n            <span data-product-price-with-tax class=\"price price--withTax\">{{price.with_tax.formatted}}</span>\n            {{#if price.without_tax}}\n                <abbr title=\"{{lang 'products.including_tax'}}\">{{lang 'products.price_with_tax' tax_label=price.tax_label}}</abbr>\n            {{/if}}\n        </div>\n    {{/if}}\n    {{#if price.without_tax}}\n        <div class=\"price-section price-section--withoutTax rrp-price--withoutTax{{#if price.with_tax}} price-section--minor{{/if}}\" {{#unless price.rrp_without_tax}}style=\"display: none;\"{{/unless}}>\n            <span>\n                {{> components/products/price-label\n                    label_value=theme_settings.pdp-retail-price-label\n                    fallback=(lang \"page_builder.pdp-retail-price-label\")\n                }}\n            </span>\n            <span data-product-rrp-price-without-tax class=\"price price--rrp\">\n                {{price.rrp_without_tax.formatted}}\n            </span>\n        </div>\n        <div class=\"price-section price-section--withoutTax non-sale-price--withoutTax{{#if price.with_tax}} price-section--minor{{/if}}\" {{#unless price.non_sale_price_without_tax}}style=\"display: none;\"{{/unless}}>\n            <span>\n                {{> components/products/price-label\n                    label_value=theme_settings.pdp-non-sale-price-label\n                    fallback=(lang \"page_builder.pdp-non-sale-price-label\")\n                }}\n            </span>\n            <span data-product-non-sale-price-without-tax class=\"price price--non-sale\">\n                {{price.non_sale_price_without_tax.formatted}}\n            </span>\n        </div>\n        <div class=\"price-section price-section--withoutTax\">\n            <span class=\"price-label\" {{#if price.non_sale_price_without_tax}}style=\"display: none;\"{{/if}}>\n                {{theme_settings.pdp-price-label}}\n            </span>\n            <span class=\"price-now-label\" {{#unless price.non_sale_price_without_tax}}style=\"display: none;\"{{/unless}}>\n                {{> components/products/price-label\n                    label_value=theme_settings.pdp-sale-price-label\n                    fallback=(lang \"page_builder.pdp-sale-price-label\")\n                }}\n            </span>\n            <span data-product-price-without-tax class=\"price price--withoutTax\">{{price.without_tax.formatted}}</span>\n            {{#if price.with_tax}}\n                <abbr title=\"{{lang 'products.excluding_tax'}}\">{{lang 'products.price_without_tax' tax_label=price.tax_label}}</abbr>\n            {{/if}}\n        </div>\n    {{/if}}\n    {{#if page_type '===' 'product'}}\n         <div class=\"price-section price-section--saving price\" {{#unless price.saved}}style=\"display: none;\"{{/unless}}>\n                <span class=\"price\">{{lang 'products.you_save_opening_text'}}</span>\n                <span data-product-price-saved class=\"price price--saving\">\n                    {{price.saved.formatted}}\n                </span>\n                <span class=\"price\">{{lang 'products.you_save_closing_bracket'}}</span>\n         </div>\n    {{/if}}\n{{/and}}\n",
  "components/products/product-aria-label": "{{#and price.price_range (if theme_settings.price_ranges '==' true)}}\n    {{#and price.price_range.min.with_tax price.price_range.max.with_tax}}\n{{lang 'category.shop_by_price_range_aria'\n       from=price.price_range.min.with_tax.formatted\n       to=price.price_range.max.with_tax.formatted\n}}\n    {{else}}\n{{lang 'category.shop_by_price_range_aria'\n       from=price.price_range.min.without_tax.formatted\n       to=price.price_range.max.without_tax.formatted\n}}\n    {{/and}}\n{{else}}\n    {{#if price.with_tax}}\n        {{#if price.non_sale_price_with_tax}}\n{{> components/products/price-label\n    label_value=theme_settings.pdp-non-sale-price-label\n    fallback=(lang \"page_builder.pdp-non-sale-price-label\")\n}}{{price.non_sale_price_with_tax.formatted}},\n{{> components/products/price-label\n    label_value=theme_settings.pdp-sale-price-label\n    fallback=(lang \"page_builder.pdp-sale-price-label\")\n}}{{price.with_tax.formatted}}\n        {{else}}\n{{price.with_tax.formatted}}\n        {{/if}}\n    {{else}}\n        {{#if price.non_sale_price_without_tax}}\n{{> components/products/price-label\n    label_value=theme_settings.pdp-non-sale-price-label\n    fallback=(lang \"page_builder.pdp-non-sale-price-label\")\n}}{{price.non_sale_price_without_tax.formatted}},\n{{> components/products/price-label\n    label_value=theme_settings.pdp-sale-price-label\n    fallback=(lang \"page_builder.pdp-sale-price-label\")\n}}{{price.without_tax.formatted}}\n        {{else}}\n{{price.without_tax.formatted}}\n        {{/if}}\n    {{/if}}\n{{/and}}\n",
  "components/common/modal/modal-close-btn": "<button class=\"modal-close\"\n        type=\"button\"\n        title=\"{{lang 'common.close'}}\"\n        {{additional_attr}}\n>\n    <span class=\"aria-description--hidden\">{{lang 'common.close'}}</span>\n    <span aria-hidden=\"true\">&#215;</span>\n</button>\n",
  "components/products/price-range": "{{#and price.retail_price_range.min.with_tax price.retail_price_range.max.with_tax}}\n    <div class=\"price-section price-section--withTax rrp-price--withTax\">\n        <span>\n            {{> components/products/price-label\n                label_value=theme_settings.pdp-retail-price-label\n                fallback=(lang \"page_builder.pdp-retail-price-label\")\n            }}\n        </span>\n        <span data-product-rrp-price-with-tax class=\"price price--rrp\">{{price.retail_price_range.min.with_tax.formatted}} - {{price.retail_price_range.max.with_tax.formatted}}</span>\n    </div>\n{{else}}\n    {{#if price.with_tax}}\n        <div class=\"price-section price-section--withTax rrp-price--withTax\" style=\"display: none;\">\n            <span>\n                {{> components/products/price-label\n                    label_value=theme_settings.pdp-retail-price-label\n                    fallback=(lang \"page_builder.pdp-retail-price-label\")\n                }}\n            </span>\n            <span data-product-rrp-with-tax class=\"price price--rrp\">\n                {{price.rrp_with_tax.formatted}}\n            </span>\n        </div>\n    {{/if}}\n{{/and}}\n{{#and price.price_range.min.with_tax price.price_range.max.with_tax}}\n    {{!-- Never display the \"non-sales price\" if there is a price range to be shown, but we do want the element on the page --}}\n    <div class=\"price-section price-section--withTax non-sale-price--withTax\" style=\"display: none;\">\n        <span>\n            {{> components/products/price-label\n                label_value=theme_settings.pdp-non-sale-price-label\n                fallback=(lang \"page_builder.pdp-non-sale-price-label\")\n            }}\n        </span>\n        <span data-product-non-sale-price-with-tax class=\"price price--non-sale\">\n            {{price.non_sale_price_with_tax.formatted}}\n        </span>\n    </div>\n    <div class=\"price-section price-section--withTax\">\n        <span class=\"price-label\">{{theme_settings.pdp-price-label}}</span>\n        <span class=\"price-now-label\" style=\"display: none;\">\n            {{> components/products/price-label\n                label_value=theme_settings.pdp-sale-price-label\n                fallback=(lang \"page_builder.pdp-sale-price-label\")\n            }}\n        </span>\n        <span data-product-price-with-tax class=\"price price--withTax\">{{price.price_range.min.with_tax.formatted}} - {{price.price_range.max.with_tax.formatted}}</span>\n        {{#and price.price_range.min.without_tax price.price_range.max.without_tax}}\n            <abbr title=\"{{lang 'products.including_tax'}}\">{{lang 'products.price_with_tax' tax_label=price.price_range.min.tax_label}}</abbr>\n        {{/and}}\n    </div>\n{{/and}}\n{{#and price.retail_price_range.min.without_tax price.retail_price_range.max.without_tax}}\n    <div class=\"price-section price-section--withoutTax rrp-price--withoutTax{{#if price.with_tax}} price-section--minor{{/if}}\">\n        <span>\n            {{> components/products/price-label\n                label_value=theme_settings.pdp-retail-price-label\n                fallback=(lang \"page_builder.pdp-retail-price-label\")\n            }}\n        </span>\n        <span data-product-rrp-price-without-tax class=\"price price--rrp\">{{price.retail_price_range.min.without_tax.formatted}} - {{price.retail_price_range.max.without_tax.formatted}}</span>\n    </div>\n{{else}}\n    {{#if price.without_tax}}\n        <div class=\"price-section price-section--withoutTax rrp-price--withoutTax{{#if price.with_tax}} price-section--minor{{/if}}\" style=\"display: none;\">\n            <span>\n                {{> components/products/price-label\n                    label_value=theme_settings.pdp-retail-price-label\n                    fallback=(lang \"page_builder.pdp-retail-price-label\")\n                }}\n            </span>\n            <span data-product-rrp-price-without-tax class=\"price price--rrp\">\n                {{price.rrp_without_tax.formatted}}\n            </span>\n        </div>\n    {{/if}}\n{{/and}}\n{{#and price.price_range.min.without_tax price.price_range.max.without_tax}}\n    {{!-- Never display the \"non-sales price\" if there is a price range to be shown, but we do want the element on the page --}}\n    <div class=\"price-section price-section--withoutTax non-sale-price--withoutTax{{#if price.with_tax}} price-section--minor{{/if}}\" style=\"display: none;\">\n        <span>\n            {{> components/products/price-label\n                label_value=theme_settings.pdp-non-sale-price-label\n                fallback=(lang \"page_builder.pdp-non-sale-price-label\")\n            }}\n        </span>\n        <span data-product-non-sale-price-without-tax class=\"price price--non-sale\">\n            {{price.non_sale_price_without_tax.formatted}}\n        </span>\n    </div>\n    <div class=\"price-section price-section--withoutTax{{#and price_range.min.with_tax price_range.max.with_tax}} price-section--minor{{/and}}\">\n        <span class=\"price-label\">{{theme_settings.pdp-price-label}}</span>\n        <span class=\"price-now-label\" style=\"display: none;\">\n            {{> components/products/price-label\n                label_value=theme_settings.pdp-sale-price-label\n                fallback=(lang \"page_builder.pdp-sale-price-label\")\n            }}\n        </span>\n        <span data-product-price-without-tax class=\"price price--withoutTax\">{{price.price_range.min.without_tax.formatted}} - {{price.price_range.max.without_tax.formatted}}</span>\n        {{#and price.price_range.min.with_tax price.price_range.max.with_tax}}\n            <abbr title=\"{{lang 'products.excluding_tax'}}\">{{lang 'products.price_without_tax' tax_label=price.price_range.min.tax_label}}</abbr>\n        {{/and}}\n    </div>\n{{/and}}\n\n{{!-- Never display the \"saving price\" element by default if there is a price range on the page to be shown --}}\n{{#if page_type '===' 'product'}}\n     <div class=\"price-section price-section--saving price\" style=\"display: none;\">\n            <span class=\"price\">{{lang 'products.you_save_opening_text'}}</span>\n            <span data-product-price-saved class=\"price price--saving\">\n                {{price.saved.formatted}}\n            </span>\n            <span class=\"price\">{{lang 'products.you_save_closing_bracket'}}</span>\n     </div>\n{{/if}}\n",
  "components/products/price-label": "{{#if label_value '===' ''}}\n    {{fallback}}\n{{else}}\n    {{label_value}}\n{{/if}}\n"
}
